mieun/__init__.py
mieun/mieun.py
mieun-0.1.0.dist-info/METADATA
mieun-0.1.0.dist-info/WHEEL
mieun-0.1.0.dist-info/top_level.txt
mieun-0.1.0.dist-info/RECORD
